pydouble_slit/__init__.py
pydouble_slit/core.py
pydouble_slit-0.0.4.dist-info/licenses/LICENSE
pydouble_slit-0.0.4.dist-info/METADATA
pydouble_slit-0.0.4.dist-info/WHEEL
pydouble_slit-0.0.4.dist-info/top_level.txt
pydouble_slit-0.0.4.dist-info/RECORD
