Metadata-Version: 2.4
Name: pydouble-slit
Version: 0.0.4
Summary: A small example package for double slit simulation
Author-email: Himanshu Mishra <himanshu.mishra469@nmims.in>
License: MIT
Classifier: Programming Language :: Python :: 3
Classifier: Operating System :: OS Independent
Requires-Python: >=3.9
License-File: LICENSE
Requires-Dist: matplotlib
Requires-Dist: numpy
Requires-Dist: scipy
Dynamic: license-file
